soap_snow/__init__.py
soap_snow/soap_snow.py
soap_snow-0.2.1.dist-info/LICENSE
soap_snow-0.2.1.dist-info/METADATA
soap_snow-0.2.1.dist-info/WHEEL
soap_snow-0.2.1.dist-info/top_level.txt
soap_snow-0.2.1.dist-info/RECORD
