Metadata-Version: 2.1
Name: soap-snow
Version: 0.2.1
Summary: Python client for interacting with the ServiceNow SOAP web service.
Home-page: https://github.com/xthehatterx/soap_snow
Author: Ezequiel M. Iglesias
Author-email: ezequiel.m.iglesias@gmail.com
License: MIT
Platform: UNKNOWN
Classifier: Programming Language :: Python :: 3
Classifier: License :: OSI Approved :: MIT License
Classifier: Operating System :: OS Independent
Requires-Python: >=3.8
Requires-Dist: requests
